cosmologix/__init__.py
cosmologix/acoustic_scale.py
cosmologix/cli.py
cosmologix/cli_tools.py
cosmologix/contours.py
cosmologix/densities.py
cosmologix/display.py
cosmologix/distances.py
cosmologix/fitter.py
cosmologix/interpolation.py
cosmologix/likelihoods.py
cosmologix/neutrinos.py
cosmologix/parameters.py
cosmologix/tools.py
cosmologix-0.9.8.dist-info/licenses/LICENSE
cosmologix-0.9.8.dist-info/METADATA
cosmologix-0.9.8.dist-info/WHEEL
cosmologix-0.9.8.dist-info/entry_points.txt
cosmologix-0.9.8.dist-info/top_level.txt
cosmologix-0.9.8.dist-info/RECORD
