Metadata-Version: 2.4
Name: cosmologix
Version: 0.9.8
Summary: Cosmological distance computations in FLRW universe using JAX
Author-email: Marc Betoule <marc.betoule@lpnhe.in2p3.fr>, Jérémy Neveu <jeremy.neveu@lpnhe.in2p3.fr>, Dylan Kuhn <dylan.kuhn@lpnhe.in2p3.fr>, Maude Le Jeune <maude.lejeune@apc.in2p3.fr>, Mathieu Bernard <mathieu.bernard@lpnhe.in2p3.fr>
License:                     GNU GENERAL PUBLIC LICENSE
Project-URL: Source Code, https://gitlab.in2p3.fr/lemaitre/cosmologix
Project-URL: Bug Tracker, https://gitlab.in2p3.fr/lemaitre/cosmologix/-/issues
Classifier: Development Status :: 3 - Alpha
Classifier: Intended Audience :: Science/Research
Classifier: License :: OSI Approved :: GNU General Public License v2 (GPLv2)
Classifier: Programming Language :: Python :: 3
Classifier: Programming Language :: Python :: 3.10
Classifier: Programming Language :: Python :: 3.11
Classifier: Programming Language :: Python :: 3.12
Classifier: Topic :: Scientific/Engineering :: Astronomy
Requires-Python: >=3.10
License-File: LICENSE
Requires-Dist: jax>=0.5.0
Requires-Dist: jaxlib>=0.5.0
Requires-Dist: numpy>=1.21.0
Requires-Dist: matplotlib>=3.4.0
Requires-Dist: requests
Requires-Dist: tqdm
Requires-Dist: astropy
Requires-Dist: typer
Requires-Dist: importlib_resources
Requires-Dist: asdf
Requires-Dist: zstandard
Provides-Extra: test
Requires-Dist: pytest>=6.0; extra == "test"
Requires-Dist: pytest-cov; extra == "test"
Requires-Dist: pyccl; extra == "test"
Requires-Dist: pyyaml; extra == "test"
Requires-Dist: black; extra == "test"
Requires-Dist: scipy; extra == "test"
Requires-Dist: camb; extra == "test"
Requires-Dist: jax_cosmo; extra == "test"
Dynamic: license-file
